alibabacloud_fc20230330/__init__.py
alibabacloud_fc20230330/client.py
alibabacloud_fc20230330/models/__init__.py
alibabacloud_fc20230330/models/_acceleration_info.py
alibabacloud_fc20230330/models/_alias.py
alibabacloud_fc20230330/models/_async_config.py
alibabacloud_fc20230330/models/_async_task.py
alibabacloud_fc20230330/models/_async_task_event.py
alibabacloud_fc20230330/models/_auth_config.py
alibabacloud_fc20230330/models/_batch_window.py
alibabacloud_fc20230330/models/_cdntrigger_config.py
alibabacloud_fc20230330/models/_cert_config.py
alibabacloud_fc20230330/models/_change_resource_group_input.py
alibabacloud_fc20230330/models/_change_resource_group_output.py
alibabacloud_fc20230330/models/_change_resource_group_request.py
alibabacloud_fc20230330/models/_change_resource_group_response.py
alibabacloud_fc20230330/models/_concurrency_config.py
alibabacloud_fc20230330/models/_cookie_session_affinity_config.py
alibabacloud_fc20230330/models/_corsconfig.py
alibabacloud_fc20230330/models/_create_alias_input.py
alibabacloud_fc20230330/models/_create_alias_request.py
alibabacloud_fc20230330/models/_create_alias_response.py
alibabacloud_fc20230330/models/_create_custom_domain_input.py
alibabacloud_fc20230330/models/_create_custom_domain_request.py
alibabacloud_fc20230330/models/_create_custom_domain_response.py
alibabacloud_fc20230330/models/_create_function_input.py
alibabacloud_fc20230330/models/_create_function_request.py
alibabacloud_fc20230330/models/_create_function_response.py
alibabacloud_fc20230330/models/_create_layer_version_input.py
alibabacloud_fc20230330/models/_create_layer_version_request.py
alibabacloud_fc20230330/models/_create_layer_version_response.py
alibabacloud_fc20230330/models/_create_session_input.py
alibabacloud_fc20230330/models/_create_session_request.py
alibabacloud_fc20230330/models/_create_session_response.py
alibabacloud_fc20230330/models/_create_trigger_input.py
alibabacloud_fc20230330/models/_create_trigger_request.py
alibabacloud_fc20230330-4.6.8.dist-info/LICENSE
alibabacloud_fc20230330-4.6.8.dist-info/METADATA
alibabacloud_fc20230330-4.6.8.dist-info/WHEEL
alibabacloud_fc20230330-4.6.8.dist-info/top_level.txt
alibabacloud_fc20230330-4.6.8.dist-info/RECORD
